fakemap/__init__.py
fakemap/fakemap.py
fakemap/foliummap.py
fakemap-0.0.6.dist-info/LICENSE
fakemap-0.0.6.dist-info/METADATA
fakemap-0.0.6.dist-info/WHEEL
fakemap-0.0.6.dist-info/dependency_links.txt
fakemap-0.0.6.dist-info/top_level.txt
fakemap-0.0.6.dist-info/RECORD
