Metadata-Version: 2.1
Name: fakemap
Version: 0.0.6
Summary: Python Boilerplate contains all the boilerplate you need to create a Python package.
Home-page: https://github.com/MattAGUT/fakemap
Author: Matthew Gerloff
Author-email: mapache.tn@gmail.com
License: MIT license
Keywords: fakemap
Classifier: Development Status :: 2 - Pre-Alpha
Classifier: Intended Audience :: Developers
Classifier: License :: OSI Approved :: MIT License
Classifier: Natural Language :: English
Classifier: Programming Language :: Python :: 3
Classifier: Programming Language :: Python :: 3.7
Classifier: Programming Language :: Python :: 3.8
Classifier: Programming Language :: Python :: 3.9
Classifier: Programming Language :: Python :: 3.10
Requires-Python: >=3.7
License-File: LICENSE
Requires-Dist: folium
Requires-Dist: ipyleaflet
Requires-Dist: geopandas
Requires-Dist: httpx
Requires-Dist: rasterio
Requires-Dist: matplotlib
